debater_python_api/__init__.py
debater_python_api/api/__init__.py
debater_python_api/api/debater_api.py
debater_python_api/api/clients/__init__.py
debater_python_api/api/clients/abstract_client.py
debater_python_api/api/clients/argument_quality_client.py
debater_python_api/api/clients/claim_and_evidence_detection_client.py
debater_python_api/api/clients/claim_boundaries_client.py
debater_python_api/api/clients/clustering_client.py
debater_python_api/api/clients/embedding_client.py
debater_python_api/api/clients/index_searcher_client.py
debater_python_api/api/clients/keypoints_admin_client.py
debater_python_api/api/clients/keypoints_client.py
debater_python_api/api/clients/keypoints_pairs_infer_client.py
debater_python_api/api/clients/narrative_generation_client.py
debater_python_api/api/clients/pro_con_client.py
debater_python_api/api/clients/term_relater_client.py
debater_python_api/api/clients/term_wikifier_client.py
debater_python_api/api/clients/theme_extraction_client.py
debater_python_api/api/clients/key_point_summarization/KpsExceptions.py
debater_python_api/api/clients/key_point_summarization/KpsResult.py
debater_python_api/api/clients/key_point_summarization/docx_generator.py
debater_python_api/api/clients/key_point_summarization/graph_generator.py
debater_python_api/api/clients/key_point_summarization/utils.py
debater_python_api/api/clients/response_data/__init__.py
debater_python_api/api/clients/response_data/speech_response.py
debater_python_api/api/sentence_level_index/__init__.py
debater_python_api/api/sentence_level_index/client/__init__.py
debater_python_api/api/sentence_level_index/client/article_retrieval_request.py
debater_python_api/api/sentence_level_index/client/elastic_client.py
debater_python_api/api/sentence_level_index/client/elastic_search_article_res.py
debater_python_api/api/sentence_level_index/client/elastic_search_sentence_res.py
debater_python_api/api/sentence_level_index/client/sentence_query_base.py
debater_python_api-5.1.4.dist-info/LICENSE
debater_python_api-5.1.4.dist-info/METADATA
debater_python_api-5.1.4.dist-info/WHEEL
debater_python_api-5.1.4.dist-info/top_level.txt
debater_python_api-5.1.4.dist-info/RECORD
