Metadata-Version: 2.1
Name: debater-python-api
Version: 5.1.4
Summary: Project Debater Early Access Program API sdk for python
Author-email: Elad Venezian <eladv@il.ibm.com>
License: Apache License
Classifier: Programming Language :: Python :: 3
Classifier: Operating System :: OS Independent
Requires-Python: >=3.6
License-File: LICENSE
Requires-Dist: requests
Requires-Dist: scikit-learn
Requires-Dist: matplotlib
Requires-Dist: numpy
Requires-Dist: pandas
Requires-Dist: python-docx
Requires-Dist: networkx
